pyactr/__init__.py
pyactr/buffers.py
pyactr/chunks.py
pyactr/declarative.py
pyactr/environment.py
pyactr/goals.py
pyactr/model.py
pyactr/motor.py
pyactr/productions.py
pyactr/simulation.py
pyactr/utilities.py
pyactr/vision.py
pyactr/tests/__init__.py
pyactr/tests/modeltests.py
pyactr/tests/tests.py
pyactr-0.3.2.dist-info/LICENSE
pyactr-0.3.2.dist-info/METADATA
pyactr-0.3.2.dist-info/WHEEL
pyactr-0.3.2.dist-info/top_level.txt
pyactr-0.3.2.dist-info/RECORD
